{"match_id": "2025020184", "start_time_utc": "2025-11-01T20:00:00", "home_team": "San Jose Sharks", "away_team": "Colorado Avalanche", "preds": {"rt": {"home": 0.3342, "draw": 0.1956, "away": 0.4701}, "ft": {"home": 0.4489, "away": 0.5511}, "mu": {"home": 2.7585, "away": 3.1242}, "std": {"home": 1.8198, "away": 1.8757}, "hcp": [{"hcp": -1.5, "prob": 0.2155}, {"hcp": -0.5, "prob": 0.358}, {"hcp": 0.5, "prob": 0.5247}, {"hcp": 1.5, "prob": 0.6861}], "ou": [{"points": 5.5, "prob": 0.5515}, {"points": 6.5, "prob": 0.4173}]}}