{"match_id": "2025020169", "start_time_utc": "2025-10-30T23:00:00", "home_team": "Tampa Bay Lightning", "away_team": "Dallas Stars", "preds": {"rt": {"home": 0.4891, "draw": 0.2289, "away": 0.282}, "ft": {"home": 0.6812, "away": 0.3188}, "mu": {"home": 3.954, "away": 2.7609}, "std": {"home": 1.877, "away": 1.8316}, "hcp": [{"hcp": -1.5, "prob": 0.4467}, {"hcp": -0.5, "prob": 0.6036}, {"hcp": 0.5, "prob": 0.746}, {"hcp": 1.5, "prob": 0.8556}], "ou": [{"points": 5.5, "prob": 0.6589}, {"points": 6.5, "prob": 0.5289}]}}