{"match_id": "2025020018", "start_time_utc": "2025-10-10T01:00:00", "home_team": "Colorado Avalanche", "away_team": "Utah Mammoth", "preds": {"rt": {"home": 0.4636, "draw": 0.1804, "away": 0.356}, "ft": {"home": 0.561, "away": 0.439}, "mu": {"home": 2.6968, "away": 2.384}, "std": {"home": 1.8568, "away": 1.8337}, "hcp": [{"hcp": -1.5, "prob": 0.2918}, {"hcp": -0.5, "prob": 0.4636}, {"hcp": 0.5, "prob": 0.644}, {"hcp": 1.5, "prob": 0.7958}], "ou": [{"points": 5.5, "prob": 0.4435}, {"points": 6.5, "prob": 0.3154}]}}