{"match_id": "2025020527", "start_time_utc": "2025-12-17T03:00:00", "home_team": "San Jose Sharks", "away_team": "Calgary Flames", "preds": {"rt": {"home": 0.2921, "draw": 0.2703, "away": 0.4377}, "ft": {"home": 0.4457, "away": 0.5543}, "mu": {"away": 3.1125, "home": 2.7535}, "std": {"away": 1.8439, "home": 1.8212}, "hcp": [{"hcp": -1.5, "prob": 0.2159}, {"hcp": -0.5, "prob": 0.3589}, {"hcp": 0.5, "prob": 0.5258}, {"hcp": 1.5, "prob": 0.6874}], "ou": [{"points": 5.5, "prob": 0.5536}, {"points": 6.5, "prob": 0.4078}]}}