{"match_id": "2025020911", "start_time_utc": "2026-02-26T00:00:00", "home_team": "Washington Capitals", "away_team": "Philadelphia Flyers", "preds": {"rt": {"home": 0.4721, "draw": 0.2251, "away": 0.3028}, "ft": {"home": 0.6026, "away": 0.3974}, "mu": {"away": 2.8817, "home": 3.4544}, "std": {"away": 1.8121, "home": 1.8239}, "hcp": [{"hcp": -1.5, "prob": 0.3979}, {"hcp": -0.5, "prob": 0.5358}, {"hcp": 0.5, "prob": 0.6698}, {"hcp": 1.5, "prob": 0.7849}], "ou": [{"points": 5.5, "prob": 0.6606}, {"points": 6.5, "prob": 0.5024}]}}