{"match_id": "2025021107", "start_time_utc": "2026-03-21T23:00:00", "home_team": "Vancouver Canucks", "away_team": "St. Louis Blues", "preds": {"rt": {"home": 0.3096, "draw": 0.2229, "away": 0.4675}, "ft": {"home": 0.4377, "away": 0.5623}, "mu": {"away": 3.4114, "home": 2.8791}, "std": {"away": 1.8239, "home": 1.8239}, "hcp": [{"hcp": -1.5, "prob": 0.2198}, {"hcp": -0.5, "prob": 0.3364}, {"hcp": 0.5, "prob": 0.4715}, {"hcp": 1.5, "prob": 0.6096}], "ou": [{"points": 5.5, "prob": 0.6298}, {"points": 6.5, "prob": 0.4741}]}}