{"match_id": "2025020673", "start_time_utc": "2026-01-07T01:00:00", "home_team": "Winnipeg Jets", "away_team": "Vegas Golden Knights", "preds": {"rt": {"home": 0.4011, "draw": 0.2314, "away": 0.3675}, "ft": {"home": 0.5417, "away": 0.4583}, "mu": {"home": 3.1364, "away": 2.8945}, "std": {"home": 1.8239, "away": 1.8239}, "hcp": [{"hcp": -1.5, "prob": 0.2984}, {"hcp": -0.5, "prob": 0.4557}, {"hcp": 0.5, "prob": 0.6211}, {"hcp": 1.5, "prob": 0.7662}], "ou": [{"points": 5.5, "prob": 0.5778}, {"points": 6.5, "prob": 0.4312}]}}