{"match_id": "2025021005", "start_time_utc": "2026-03-08T23:00:00", "home_team": "New Jersey Devils", "away_team": "Detroit Red Wings", "preds": {"rt": {"home": 0.4272, "draw": 0.2423, "away": 0.3306}, "ft": {"home": 0.5665, "away": 0.4335}, "mu": {"away": 2.6532, "home": 2.9621}, "std": {"away": 1.8117, "home": 1.8243}, "hcp": [{"hcp": -1.5, "prob": 0.3427}, {"hcp": -0.5, "prob": 0.4863}, {"hcp": 0.5, "prob": 0.6322}, {"hcp": 1.5, "prob": 0.7608}], "ou": [{"points": 5.5, "prob": 0.5476}, {"points": 6.5, "prob": 0.3876}]}}