{"match_id": "2025021216", "start_time_utc": "2026-04-04T23:00:00", "home_team": "Vancouver Canucks", "away_team": "Utah Mammoth", "preds": {"rt": {"home": 0.2618, "draw": 0.2057, "away": 0.5325}, "ft": {"home": 0.3789, "away": 0.6211}, "mu": {"away": 3.887, "home": 2.9319}, "std": {"away": 1.8239, "home": 1.8239}, "hcp": [{"hcp": -1.5, "prob": 0.1757}, {"hcp": -0.5, "prob": 0.276}, {"hcp": 0.5, "prob": 0.3984}, {"hcp": 1.5, "prob": 0.5314}], "ou": [{"points": 5.5, "prob": 0.7014}, {"points": 6.5, "prob": 0.5543}]}}