{"match_id": "2025021097", "start_time_utc": "2026-03-21T01:00:00", "home_team": "Calgary Flames", "away_team": "Florida Panthers", "preds": {"rt": {"home": 0.247, "draw": 0.4091, "away": 0.3439}, "ft": {"home": 0.4829, "away": 0.5171}, "mu": {"away": 3.0102, "home": 2.6134}, "std": {"away": 1.8239, "home": 1.8239}, "hcp": [{"hcp": -1.5, "prob": 0.2713}, {"hcp": -0.5, "prob": 0.3867}, {"hcp": 0.5, "prob": 0.5132}, {"hcp": 1.5, "prob": 0.6384}], "ou": [{"points": 5.5, "prob": 0.5477}, {"points": 6.5, "prob": 0.3915}]}}