{"match_id": "0022500270", "start_time_utc": "2025-11-23T00:00:00", "home_team": "New Orleans Pelicans", "away_team": "Atlanta Hawks", "preds": {"rt": {"home": 0.1731, "draw": 0.0174, "away": 0.8096}, "ft": {"home": 0.1824, "away": 0.8176}, "mu": {"away": 122.292, "home": 108.4861}, "std": {"away": 11.8455, "home": 12.0532}, "hcp": [{"hcp": -10.5, "prob": 0.0546}, {"hcp": -9.5, "prob": 0.0623}, {"hcp": -8.5, "prob": 0.0708}, {"hcp": -7.5, "prob": 0.0802}, {"hcp": -6.5, "prob": 0.0905}, {"hcp": -5.5, "prob": 0.1017}, {"hcp": -4.5, "prob": 0.1139}, {"hcp": -3.5, "prob": 0.1272}, {"hcp": -2.5, "prob": 0.1414}, {"hcp": -1.5, "prob": 0.1567}, {"hcp": -0.5, "prob": 0.1731}, {"hcp": 0.5, "prob": 0.1904}, {"hcp": 1.5, "prob": 0.2089}, {"hcp": 2.5, "prob": 0.2283}, {"hcp": 3.5, "prob": 0.2487}, {"hcp": 4.5, "prob": 0.2701}, {"hcp": 5.5, "prob": 0.2923}, {"hcp": 6.5, "prob": 0.3153}, {"hcp": 7.5, "prob": 0.3391}, {"hcp": 8.5, "prob": 0.3636}, {"hcp": 9.5, "prob": 0.3886}, {"hcp": 10.5, "prob": 0.414}], "ou": [{"points": 220.5, "prob": 0.7046}, {"points": 221.5, "prob": 0.6863}, {"points": 222.5, "prob": 0.6675}, {"points": 223.5, "prob": 0.6483}, {"points": 224.5, "prob": 0.6287}, {"points": 225.5, "prob": 0.6087}, {"points": 226.5, "prob": 0.5885}, {"points": 227.5, "prob": 0.5681}, {"points": 228.5, "prob": 0.5474}, {"points": 229.5, "prob": 0.5266}, {"points": 230.5, "prob": 0.5058}]}}