{"match_id": "0022500072", "start_time_utc": "2025-11-29T00:30:00", "home_team": "Detroit Pistons", "away_team": "Orlando Magic", "preds": {"rt": {"home": 0.5934, "draw": 0.0246, "away": 0.382}, "ft": {"home": 0.6067, "away": 0.3933}, "mu": {"home": 124.4719, "away": 120.2761}, "std": {"home": 10.1344, "away": 10.3004}, "hcp": [{"hcp": -10.5, "prob": 0.3433}, {"hcp": -9.5, "prob": 0.3671}, {"hcp": -8.5, "prob": 0.3915}, {"hcp": -7.5, "prob": 0.4162}, {"hcp": -6.5, "prob": 0.4413}, {"hcp": -5.5, "prob": 0.4667}, {"hcp": -4.5, "prob": 0.4922}, {"hcp": -3.5, "prob": 0.5177}, {"hcp": -2.5, "prob": 0.5431}, {"hcp": -1.5, "prob": 0.5684}, {"hcp": -0.5, "prob": 0.5934}, {"hcp": 0.5, "prob": 0.618}, {"hcp": 1.5, "prob": 0.6421}, {"hcp": 2.5, "prob": 0.6657}, {"hcp": 3.5, "prob": 0.6887}, {"hcp": 4.5, "prob": 0.7109}, {"hcp": 5.5, "prob": 0.7324}, {"hcp": 6.5, "prob": 0.753}, {"hcp": 7.5, "prob": 0.7728}, {"hcp": 8.5, "prob": 0.7916}, {"hcp": 9.5, "prob": 0.8095}, {"hcp": 10.5, "prob": 0.8263}], "ou": [{"points": 220.5, "prob": 0.931}, {"points": 221.5, "prob": 0.9225}, {"points": 222.5, "prob": 0.9132}, {"points": 223.5, "prob": 0.9032}, {"points": 224.5, "prob": 0.8922}, {"points": 225.5, "prob": 0.8805}, {"points": 226.5, "prob": 0.8678}, {"points": 227.5, "prob": 0.8543}, {"points": 228.5, "prob": 0.8399}, {"points": 229.5, "prob": 0.8245}, {"points": 230.5, "prob": 0.8083}]}}