{"match_id": "0022500060", "start_time_utc": "2025-11-26T22:00:00", "home_team": "Boston Celtics", "away_team": "Detroit Pistons", "preds": {"rt": {"home": 0.5148, "draw": 0.0259, "away": 0.4593}, "ft": {"home": 0.5288, "away": 0.4712}, "mu": {"home": 119.0105, "away": 117.9382}, "std": {"home": 11.7856, "away": 9.9574}, "hcp": [{"hcp": -10.5, "prob": 0.27}, {"hcp": -9.5, "prob": 0.2919}, {"hcp": -8.5, "prob": 0.3146}, {"hcp": -7.5, "prob": 0.338}, {"hcp": -6.5, "prob": 0.3621}, {"hcp": -5.5, "prob": 0.3867}, {"hcp": -4.5, "prob": 0.4118}, {"hcp": -3.5, "prob": 0.4373}, {"hcp": -2.5, "prob": 0.463}, {"hcp": -1.5, "prob": 0.4889}, {"hcp": -0.5, "prob": 0.5148}, {"hcp": 0.5, "prob": 0.5407}, {"hcp": 1.5, "prob": 0.5664}, {"hcp": 2.5, "prob": 0.5918}, {"hcp": 3.5, "prob": 0.6168}, {"hcp": 4.5, "prob": 0.6414}, {"hcp": 5.5, "prob": 0.6654}, {"hcp": 6.5, "prob": 0.6887}, {"hcp": 7.5, "prob": 0.7113}, {"hcp": 8.5, "prob": 0.7331}, {"hcp": 9.5, "prob": 0.754}, {"hcp": 10.5, "prob": 0.774}], "ou": [{"points": 220.5, "prob": 0.8274}, {"points": 221.5, "prob": 0.8123}, {"points": 222.5, "prob": 0.7964}, {"points": 223.5, "prob": 0.7798}, {"points": 224.5, "prob": 0.7625}, {"points": 225.5, "prob": 0.7444}, {"points": 226.5, "prob": 0.7256}, {"points": 227.5, "prob": 0.7061}, {"points": 228.5, "prob": 0.6861}, {"points": 229.5, "prob": 0.6654}, {"points": 230.5, "prob": 0.6443}]}}