{"match_id": "0022500772", "start_time_utc": "2026-02-11T01:00:00", "home_team": "Houston Rockets", "away_team": "Los Angeles Clippers", "preds": {"rt": {"home": 0.5265, "draw": 0.0528, "away": 0.4207}, "ft": {"home": 0.5735, "away": 0.4265}, "mu": {"away": 108.7208, "home": 110.8512}, "std": {"away": 10.9059, "home": 11.6941}, "hcp": [{"hcp": -10.5, "prob": 0.2859}, {"hcp": -9.5, "prob": 0.3093}, {"hcp": -8.5, "prob": 0.3335}, {"hcp": -7.5, "prob": 0.3584}, {"hcp": -6.5, "prob": 0.3839}, {"hcp": -5.5, "prob": 0.4099}, {"hcp": -4.5, "prob": 0.4364}, {"hcp": -3.5, "prob": 0.4631}, {"hcp": -2.5, "prob": 0.49}, {"hcp": -1.5, "prob": 0.5169}, {"hcp": -0.5, "prob": 0.5438}, {"hcp": 0.5, "prob": 0.5705}, {"hcp": 1.5, "prob": 0.5968}, {"hcp": 2.5, "prob": 0.6227}, {"hcp": 3.5, "prob": 0.6481}, {"hcp": 4.5, "prob": 0.6728}, {"hcp": 5.5, "prob": 0.6968}, {"hcp": 6.5, "prob": 0.72}, {"hcp": 7.5, "prob": 0.7422}, {"hcp": 8.5, "prob": 0.7636}, {"hcp": 9.5, "prob": 0.7839}, {"hcp": 10.5, "prob": 0.8031}], "ou": [{"points": 220.5, "prob": 0.4843}, {"points": 221.5, "prob": 0.4629}, {"points": 222.5, "prob": 0.4415}, {"points": 223.5, "prob": 0.4203}, {"points": 224.5, "prob": 0.3994}, {"points": 225.5, "prob": 0.3787}, {"points": 226.5, "prob": 0.3584}, {"points": 227.5, "prob": 0.3385}, {"points": 228.5, "prob": 0.3191}, {"points": 229.5, "prob": 0.3001}, {"points": 230.5, "prob": 0.2817}, {"points": 231.5, "prob": 0.2638}, {"points": 232.5, "prob": 0.2466}, {"points": 233.5, "prob": 0.23}, {"points": 234.5, "prob": 0.214}, {"points": 235.5, "prob": 0.1988}, {"points": 236.5, "prob": 0.1842}, {"points": 237.5, "prob": 0.1703}, {"points": 238.5, "prob": 0.1571}, {"points": 239.5, "prob": 0.1446}, {"points": 240.5, "prob": 0.1328}]}}