{"match_id": "0022501017", "start_time_utc": "2026-03-20T23:30:00", "home_team": "Detroit Pistons", "away_team": "Golden State Warriors", "preds": {"rt": {"home": 0.676, "draw": 0.0461, "away": 0.2779}, "ft": {"home": 0.7409, "away": 0.2591}, "mu": {"away": 106.8731, "home": 115.2661}, "std": {"away": 11.3516, "home": 11.6261}, "hcp": [{"hcp": -10.5, "prob": 0.4436}, {"hcp": -9.5, "prob": 0.4702}, {"hcp": -8.5, "prob": 0.497}, {"hcp": -7.5, "prob": 0.5237}, {"hcp": -6.5, "prob": 0.5504}, {"hcp": -5.5, "prob": 0.5769}, {"hcp": -4.5, "prob": 0.603}, {"hcp": -3.5, "prob": 0.6286}, {"hcp": -2.5, "prob": 0.6537}, {"hcp": -1.5, "prob": 0.6781}, {"hcp": -0.5, "prob": 0.7018}, {"hcp": 0.5, "prob": 0.7247}, {"hcp": 1.5, "prob": 0.7466}, {"hcp": 2.5, "prob": 0.7677}, {"hcp": 3.5, "prob": 0.7877}, {"hcp": 4.5, "prob": 0.8066}, {"hcp": 5.5, "prob": 0.8245}, {"hcp": 6.5, "prob": 0.8413}, {"hcp": 7.5, "prob": 0.857}, {"hcp": 8.5, "prob": 0.8716}, {"hcp": 9.5, "prob": 0.8852}, {"hcp": 10.5, "prob": 0.8977}], "ou": [{"points": 220.5, "prob": 0.5389}, {"points": 221.5, "prob": 0.5178}, {"points": 222.5, "prob": 0.4966}, {"points": 223.5, "prob": 0.4754}, {"points": 224.5, "prob": 0.4544}, {"points": 225.5, "prob": 0.4334}, {"points": 226.5, "prob": 0.4126}, {"points": 227.5, "prob": 0.3921}, {"points": 228.5, "prob": 0.3719}, {"points": 229.5, "prob": 0.3521}, {"points": 230.5, "prob": 0.3326}, {"points": 231.5, "prob": 0.3136}, {"points": 232.5, "prob": 0.2951}, {"points": 233.5, "prob": 0.2771}, {"points": 234.5, "prob": 0.2597}, {"points": 235.5, "prob": 0.2429}, {"points": 236.5, "prob": 0.2267}, {"points": 237.5, "prob": 0.2111}, {"points": 238.5, "prob": 0.1962}, {"points": 239.5, "prob": 0.182}, {"points": 240.5, "prob": 0.1684}]}}