{"match_id": "0022501119", "start_time_utc": "2026-04-03T02:30:00", "home_team": "Los Angeles Clippers", "away_team": "San Antonio Spurs", "preds": {"rt": {"home": 0.3237, "draw": 0.0338, "away": 0.6424}, "ft": {"home": 0.3228, "away": 0.6772}, "mu": {"away": 119.9069, "home": 112.5413}, "std": {"away": 11.6567, "home": 11.5724}, "hcp": [{"hcp": -10.5, "prob": 0.1012}, {"hcp": -9.5, "prob": 0.1144}, {"hcp": -8.5, "prob": 0.1288}, {"hcp": -7.5, "prob": 0.1444}, {"hcp": -6.5, "prob": 0.1612}, {"hcp": -5.5, "prob": 0.1793}, {"hcp": -4.5, "prob": 0.1986}, {"hcp": -3.5, "prob": 0.219}, {"hcp": -2.5, "prob": 0.2407}, {"hcp": -1.5, "prob": 0.2635}, {"hcp": -0.5, "prob": 0.2873}, {"hcp": 0.5, "prob": 0.3121}, {"hcp": 1.5, "prob": 0.3378}, {"hcp": 2.5, "prob": 0.3642}, {"hcp": 3.5, "prob": 0.3913}, {"hcp": 4.5, "prob": 0.419}, {"hcp": 5.5, "prob": 0.447}, {"hcp": 6.5, "prob": 0.4754}, {"hcp": 7.5, "prob": 0.5038}, {"hcp": 8.5, "prob": 0.5323}, {"hcp": 9.5, "prob": 0.5605}, {"hcp": 10.5, "prob": 0.5885}], "ou": [{"points": 220.5, "prob": 0.7372}, {"points": 221.5, "prob": 0.7199}, {"points": 222.5, "prob": 0.702}, {"points": 223.5, "prob": 0.6837}, {"points": 224.5, "prob": 0.6648}, {"points": 225.5, "prob": 0.6456}, {"points": 226.5, "prob": 0.6259}, {"points": 227.5, "prob": 0.606}, {"points": 228.5, "prob": 0.5857}, {"points": 229.5, "prob": 0.5653}, {"points": 230.5, "prob": 0.5446}, {"points": 231.5, "prob": 0.5238}, {"points": 232.5, "prob": 0.503}, {"points": 233.5, "prob": 0.4822}, {"points": 234.5, "prob": 0.4614}, {"points": 235.5, "prob": 0.4407}, {"points": 236.5, "prob": 0.4202}, {"points": 237.5, "prob": 0.4}, {"points": 238.5, "prob": 0.3799}, {"points": 239.5, "prob": 0.3603}, {"points": 240.5, "prob": 0.3409}]}}