{"match_id": "0022500713", "start_time_utc": "2026-02-03T00:00:00", "home_team": "Indiana Pacers", "away_team": "Houston Rockets", "preds": {"rt": {"home": 0.4058, "draw": 0.0524, "away": 0.5418}, "ft": {"home": 0.4251, "away": 0.5749}, "mu": {"away": 111.6937, "home": 108.942}, "std": {"away": 12.4501, "home": 11.4809}, "hcp": [{"hcp": -10.5, "prob": 0.186}, {"hcp": -9.5, "prob": 0.2046}, {"hcp": -8.5, "prob": 0.2242}, {"hcp": -7.5, "prob": 0.2449}, {"hcp": -6.5, "prob": 0.2666}, {"hcp": -5.5, "prob": 0.2892}, {"hcp": -4.5, "prob": 0.3126}, {"hcp": -3.5, "prob": 0.3369}, {"hcp": -2.5, "prob": 0.3618}, {"hcp": -1.5, "prob": 0.3873}, {"hcp": -0.5, "prob": 0.4133}, {"hcp": 0.5, "prob": 0.4398}, {"hcp": 1.5, "prob": 0.4665}, {"hcp": 2.5, "prob": 0.4933}, {"hcp": 3.5, "prob": 0.5202}, {"hcp": 4.5, "prob": 0.5469}, {"hcp": 5.5, "prob": 0.5735}, {"hcp": 6.5, "prob": 0.5997}, {"hcp": 7.5, "prob": 0.6255}, {"hcp": 8.5, "prob": 0.6508}, {"hcp": 9.5, "prob": 0.6754}, {"hcp": 10.5, "prob": 0.6992}], "ou": [{"points": 220.5, "prob": 0.5068}, {"points": 221.5, "prob": 0.4865}, {"points": 222.5, "prob": 0.4662}, {"points": 223.5, "prob": 0.446}, {"points": 224.5, "prob": 0.426}, {"points": 225.5, "prob": 0.4061}, {"points": 226.5, "prob": 0.3865}, {"points": 227.5, "prob": 0.3672}, {"points": 228.5, "prob": 0.3482}, {"points": 229.5, "prob": 0.3296}, {"points": 230.5, "prob": 0.3114}, {"points": 231.5, "prob": 0.2937}, {"points": 232.5, "prob": 0.2765}, {"points": 233.5, "prob": 0.2598}, {"points": 234.5, "prob": 0.2436}, {"points": 235.5, "prob": 0.228}, {"points": 236.5, "prob": 0.213}, {"points": 237.5, "prob": 0.1986}, {"points": 238.5, "prob": 0.1848}, {"points": 239.5, "prob": 0.1716}, {"points": 240.5, "prob": 0.1591}]}}