{"match_id": "0022500565", "start_time_utc": "2026-01-14T01:00:00", "home_team": "Houston Rockets", "away_team": "Chicago Bulls", "preds": {"rt": {"home": 0.7196, "draw": 0.022, "away": 0.2585}, "ft": {"home": 0.731, "away": 0.269}, "mu": {"home": 117.7398, "away": 108.4941}, "std": {"home": 12.0022, "away": 12.2725}, "hcp": [{"hcp": -10.5, "prob": 0.4666}, {"hcp": -9.5, "prob": 0.4931}, {"hcp": -8.5, "prob": 0.5196}, {"hcp": -7.5, "prob": 0.5461}, {"hcp": -6.5, "prob": 0.5723}, {"hcp": -5.5, "prob": 0.5982}, {"hcp": -4.5, "prob": 0.6237}, {"hcp": -3.5, "prob": 0.6487}, {"hcp": -2.5, "prob": 0.6731}, {"hcp": -1.5, "prob": 0.6967}, {"hcp": -0.5, "prob": 0.7196}, {"hcp": 0.5, "prob": 0.7415}, {"hcp": 1.5, "prob": 0.7626}, {"hcp": 2.5, "prob": 0.7827}, {"hcp": 3.5, "prob": 0.8017}, {"hcp": 4.5, "prob": 0.8197}, {"hcp": 5.5, "prob": 0.8367}, {"hcp": 6.5, "prob": 0.8526}, {"hcp": 7.5, "prob": 0.8674}, {"hcp": 8.5, "prob": 0.8811}, {"hcp": 9.5, "prob": 0.8938}, {"hcp": 10.5, "prob": 0.9055}], "ou": [{"points": 220.5, "prob": 0.6249}, {"points": 221.5, "prob": 0.6037}, {"points": 222.5, "prob": 0.5822}, {"points": 223.5, "prob": 0.5603}, {"points": 224.5, "prob": 0.5384}, {"points": 225.5, "prob": 0.5163}, {"points": 226.5, "prob": 0.4941}, {"points": 227.5, "prob": 0.472}, {"points": 228.5, "prob": 0.4499}, {"points": 229.5, "prob": 0.428}, {"points": 230.5, "prob": 0.4063}, {"points": 231.5, "prob": 0.385}, {"points": 232.5, "prob": 0.3639}, {"points": 233.5, "prob": 0.3433}, {"points": 234.5, "prob": 0.3231}, {"points": 235.5, "prob": 0.3034}, {"points": 236.5, "prob": 0.2843}, {"points": 237.5, "prob": 0.2657}, {"points": 238.5, "prob": 0.2478}, {"points": 239.5, "prob": 0.2306}, {"points": 240.5, "prob": 0.2141}]}}