{"match_id": "0022500627", "start_time_utc": "2026-01-23T00:00:00", "home_team": "Orlando Magic", "away_team": "Charlotte Hornets", "preds": {"rt": {"home": 0.6541, "draw": 0.0469, "away": 0.2991}, "ft": {"home": 0.7176, "away": 0.2824}, "mu": {"away": 110.6153, "home": 118.1386}, "std": {"away": 11.4812, "home": 12.049}, "hcp": [{"hcp": -10.5, "prob": 0.4218}, {"hcp": -9.5, "prob": 0.4478}, {"hcp": -8.5, "prob": 0.4741}, {"hcp": -7.5, "prob": 0.5005}, {"hcp": -6.5, "prob": 0.5268}, {"hcp": -5.5, "prob": 0.5531}, {"hcp": -4.5, "prob": 0.5791}, {"hcp": -3.5, "prob": 0.6048}, {"hcp": -2.5, "prob": 0.6301}, {"hcp": -1.5, "prob": 0.6548}, {"hcp": -0.5, "prob": 0.6788}, {"hcp": 0.5, "prob": 0.7021}, {"hcp": 1.5, "prob": 0.7247}, {"hcp": 2.5, "prob": 0.7463}, {"hcp": 3.5, "prob": 0.767}, {"hcp": 4.5, "prob": 0.7868}, {"hcp": 5.5, "prob": 0.8055}, {"hcp": 6.5, "prob": 0.8232}, {"hcp": 7.5, "prob": 0.8399}, {"hcp": 8.5, "prob": 0.8554}, {"hcp": 9.5, "prob": 0.87}, {"hcp": 10.5, "prob": 0.8834}], "ou": [{"points": 220.5, "prob": 0.6695}, {"points": 221.5, "prob": 0.6505}, {"points": 222.5, "prob": 0.6311}, {"points": 223.5, "prob": 0.6113}, {"points": 224.5, "prob": 0.5913}, {"points": 225.5, "prob": 0.5711}, {"points": 226.5, "prob": 0.5506}, {"points": 227.5, "prob": 0.53}, {"points": 228.5, "prob": 0.5094}, {"points": 229.5, "prob": 0.4887}, {"points": 230.5, "prob": 0.4681}, {"points": 231.5, "prob": 0.4475}, {"points": 232.5, "prob": 0.4271}, {"points": 233.5, "prob": 0.4069}, {"points": 234.5, "prob": 0.387}, {"points": 235.5, "prob": 0.3673}, {"points": 236.5, "prob": 0.348}, {"points": 237.5, "prob": 0.3291}, {"points": 238.5, "prob": 0.3106}, {"points": 239.5, "prob": 0.2926}, {"points": 240.5, "prob": 0.2751}]}}