{"match_id": "0022501036", "start_time_utc": "2026-03-23T01:00:00", "home_team": "Phoenix Suns", "away_team": "Toronto Raptors", "preds": {"rt": {"home": 0.3756, "draw": 0.0699, "away": 0.5545}, "ft": {"home": 0.3909, "away": 0.6091}, "mu": {"away": 115.5205, "home": 111.3497}, "std": {"away": 11.6807, "home": 11.8435}, "hcp": [{"hcp": -10.5, "prob": 0.1506}, {"hcp": -9.5, "prob": 0.1677}, {"hcp": -8.5, "prob": 0.186}, {"hcp": -7.5, "prob": 0.2054}, {"hcp": -6.5, "prob": 0.226}, {"hcp": -5.5, "prob": 0.2478}, {"hcp": -4.5, "prob": 0.2706}, {"hcp": -3.5, "prob": 0.2944}, {"hcp": -2.5, "prob": 0.3191}, {"hcp": -1.5, "prob": 0.3447}, {"hcp": -0.5, "prob": 0.371}, {"hcp": 0.5, "prob": 0.3979}, {"hcp": 1.5, "prob": 0.4254}, {"hcp": 2.5, "prob": 0.4531}, {"hcp": 3.5, "prob": 0.4811}, {"hcp": 4.5, "prob": 0.5093}, {"hcp": 5.5, "prob": 0.5373}, {"hcp": 6.5, "prob": 0.5652}, {"hcp": 7.5, "prob": 0.5927}, {"hcp": 8.5, "prob": 0.6198}, {"hcp": 9.5, "prob": 0.6464}, {"hcp": 10.5, "prob": 0.6722}], "ou": [{"points": 220.5, "prob": 0.6326}, {"points": 221.5, "prob": 0.613}, {"points": 222.5, "prob": 0.5931}, {"points": 223.5, "prob": 0.573}, {"points": 224.5, "prob": 0.5527}, {"points": 225.5, "prob": 0.5322}, {"points": 226.5, "prob": 0.5117}, {"points": 227.5, "prob": 0.4911}, {"points": 228.5, "prob": 0.4705}, {"points": 229.5, "prob": 0.4501}, {"points": 230.5, "prob": 0.4297}, {"points": 231.5, "prob": 0.4096}, {"points": 232.5, "prob": 0.3897}, {"points": 233.5, "prob": 0.3701}, {"points": 234.5, "prob": 0.3508}, {"points": 235.5, "prob": 0.332}, {"points": 236.5, "prob": 0.3135}, {"points": 237.5, "prob": 0.2955}, {"points": 238.5, "prob": 0.278}, {"points": 239.5, "prob": 0.2611}, {"points": 240.5, "prob": 0.2447}]}}